{
  "type": "FeatureCollection",
  "features": [
    {
      "type": "Feature",
      "properties": {},
      "geometry": {
        "coordinates": [
          [
            [
              101.41820881137113,
              0.5900214734405296
            ],
            [
              101.41848611845433,
              0.5893744578470859
            ],
            [
              101.4186709898446,
              0.5892774055019174
            ],
            [
              101.41878653446304,
              0.5891664885337633
            ],
            [
              101.41891132265096,
              0.5891248946695953
            ],
            [
              101.41909619404129,
              0.5891757316132242
            ],
            [
              101.41923946936839,
              0.5891064085076607
            ],
            [
              101.41929493078447,
              0.5890648146430095
            ],
            [
              101.41945207146597,
              0.5891757316132242
            ],
            [
              101.41965542999401,
              0.5891480023719424
            ],
            [
              101.41984030138423,
              0.5890509500213881
            ],
            [
              101.4199003845851,
              0.5891572454528671
            ],
            [
              101.41998819849618,
              0.5891618669933649
            ],
            [
              101.42008525597538,
              0.5891988393153298
            ],
            [
              101.42068608799116,
              0.5888337376146353
            ],
            [
              101.42108356147907,
              0.5889307899674776
            ],
            [
              101.42132389428536,
              0.5899105564872258
            ],
            [
              101.42086633759664,
              0.5898273687696189
            ],
            [
              101.42062138300554,
              0.5898319903095626
            ],
            [
              101.42035794127526,
              0.5898643410887132
            ],
            [
              101.4200529034818,
              0.5899845011225295
            ],
            [
              101.41982181424504,
              0.5901323903916591
            ],
            [
              101.41972013498105,
              0.5902433073405717
            ],
            [
              101.41960921214746,
              0.5901601196294877
            ],
            [
              101.41820881137113,
              0.5900214734405296
            ]
          ]
        ],
        "type": "Polygon"
      }
    }
  ]
}